{
    "version": "5.3.0",
    "flags": {},
    "shapes": [
        {
            "label": "weld",
            "points": [
                [
                    32.0,
                    701.8178506375228
                ],
                [
                    36.0,
                    710.8178506375228
                ],
                [
                    46.81056466302368,
                    754.4189435336976
                ],
                [
                    55.189435336976324,
                    784.1092896174864
                ],
                [
                    58.10382513661202,
                    783.3806921675774
                ],
                [
                    60.10746812386157,
                    779.009107468124
                ],
                [
                    62.111111111111114,
                    772.2695810564663
                ],
                [
                    65.38979963570127,
                    767.1693989071039
                ],
                [
                    68.4863387978142,
                    763.7085610200364
                ],
                [
                    71.4007285974499,
                    765.5300546448087
                ],
                [
                    73.58652094717668,
                    770.9945355191257
                ],
                [
                    74.0,
                    779.8178506375228
                ],
                [
                    77.0,
                    785.8178506375228
                ],
                [
                    77.04735883424408,
                    794.4918032786885
                ],
                [
                    79.23315118397085,
                    800.3205828779601
                ],
                [
                    81.05464480874316,
                    805.056466302368
                ],
                [
                    85.60837887067395,
                    804.6921675774136
                ],
                [
                    90.34426229508196,
                    804.1457194899818
                ],
                [
                    93.9872495446266,
                    800.6848816029145
                ],
                [
                    97.63023679417121,
                    796.6775956284154
                ],
                [
                    103.45901639344261,
                    795.7668488160292
                ],
                [
                    112.20218579234972,
                    800.1384335154828
                ],
                [
                    118.21311475409836,
                    798.1347905282332
                ],
                [
                    124.8,
                    836.8
                ],
                [
                    129.6,
                    899.6
                ],
                [
                    138.8,
                    820.0
                ],
                [
                    138.8,
                    805.2
                ],
                [
                    140.8,
                    796.0
                ],
                [
                    143.6,
                    790.0
                ],
                [
                    143.6,
                    786.0
                ],
                [
                    148.4,
                    778.8
                ],
                [
                    148.0,
                    768.8
                ],
                [
                    151.6,
                    758.4
                ],
                [
                    150.0,
                    745.8178506375228
                ],
                [
                    155.0,
                    728.8178506375228
                ],
                [
                    160.0,
                    721.8178506375228
                ],
                [
                    164.0,
                    721.8178506375228
                ],
                [
                    169.0,
                    718.8178506375228
                ],
                [
                    178.0,
                    718.8178506375228
                ],
                [
                    181.0,
                    723.8178506375228
                ],
                [
                    183.0,
                    723.8178506375228
                ],
                [
                    188.0,
                    716.8178506375228
                ],
                [
                    190.0,
                    716.8178506375228
                ],
                [
                    194.0,
                    721.8178506375228
                ],
                [
                    196.0,
                    721.8178506375228
                ],
                [
                    201.0,
                    717.8178506375228
                ],
                [
                    205.0,
                    709.8178506375228
                ],
                [
                    217.0,
                    718.8178506375228
                ],
                [
                    222.0,
                    709.8178506375228
                ],
                [
                    226.0,
                    709.8178506375228
                ],
                [
                    229.0,
                    706.8178506375228
                ],
                [
                    232.0,
                    706.8178506375228
                ],
                [
                    238.0,
                    708.8178506375228
                ],
                [
                    245.0,
                    714.8178506375228
                ],
                [
                    252.0,
                    728.8178506375228
                ],
                [
                    263.0,
                    716.8178506375228
                ],
                [
                    267.0,
                    718.8178506375228
                ],
                [
                    281.0,
                    717.8178506375228
                ],
                [
                    290.0,
                    727.8178506375228
                ],
                [
                    299.6,
                    724.8
                ],
                [
                    298.8,
                    455.6
                ],
                [
                    292.0,
                    454.8
                ],
                [
                    281.60109289617486,
                    447.8615664845174
                ],
                [
                    275.9544626593807,
                    448.59016393442636
                ],
                [
                    272.0,
                    450.81785063752284
                ],
                [
                    268.0,
                    451.81785063752284
                ],
                [
                    266.0,
                    454.81785063752284
                ],
                [
                    263.0,
                    454.81785063752284
                ],
                [
                    255.0,
                    460.81785063752284
                ],
                [
                    246.81056466302368,
                    457.1511839708562
                ],
                [
                    241.52823315118397,
                    454.601092896175
                ],
                [
                    234.0,
                    454.81785063752284
                ],
                [
                    224.0,
                    454.81785063752284
                ],
                [
                    222.0,
                    460.81785063752284
                ],
                [
                    219.6703096539162,
                    460.79417122040087
                ],
                [
                    212.74863387978144,
                    462.06921675774146
                ],
                [
                    205.0,
                    460.81785063752284
                ],
                [
                    199.45173041894353,
                    464.9836065573772
                ],
                [
                    194.71584699453553,
                    463.70856102003654
                ],
                [
                    190.0,
                    463.81785063752284
                ],
                [
                    187.0,
                    463.81785063752284
                ],
                [
                    183.0,
                    467.81785063752284
                ],
                [
                    178.0,
                    459.81785063752284
                ],
                [
                    169.76138433515484,
                    456.7868852459018
                ],
                [
                    164.11475409836066,
                    460.24772313296916
                ],
                [
                    157.0,
                    467.81785063752284
                ],
                [
                    151.36429872495447,
                    479.009107468124
                ],
                [
                    147.53916211293262,
                    480.6484517304191
                ],
                [
                    144.0783242258652,
                    479.37340619307844
                ],
                [
                    138.06739526411658,
                    479.009107468124
                ],
                [
                    133.33151183970855,
                    485.0200364298726
                ],
                [
                    130.23497267759564,
                    486.2950819672132
                ],
                [
                    125.4990892531876,
                    483.56284153005475
                ],
                [
                    121.0,
                    477.81785063752284
                ],
                [
                    117.0,
                    465.81785063752284
                ],
                [
                    115.0,
                    463.81785063752284
                ],
                [
                    111.0,
                    463.81785063752284
                ],
                [
                    108.0,
                    460.81785063752284
                ],
                [
                    97.6,
                    457.2
                ],
                [
                    90.0,
                    464.0
                ],
                [
                    83.2,
                    465.2
                ],
                [
                    79.6,
                    458.8
                ],
                [
                    71.6,
                    454.8
                ],
                [
                    65.6,
                    460.8
                ],
                [
                    60.0,
                    471.6
                ],
                [
                    55.0,
                    481.81785063752284
                ],
                [
                    46.992714025500916,
                    497.04189435336986
                ],
                [
                    42.0,
                    507.81785063752284
                ],
                [
                    36.0,
                    526.8178506375228
                ],
                [
                    32.0,
                    614.8178506375228
                ]
            ],
            "group_id": null,
            "description": null,
            "shape_type": "polygon",
            "flags": {}
        }
    ],
    "imagePath": "1694353019.png",
    "imageData": null,
    "imageHeight": 1248,
    "imageWidth": 1248
}