{
    "version": "5.3.0",
    "flags": {},
    "shapes": [
        {
            "label": "weld",
            "points": [
                [
                    35.33515482695811,
                    695.0382513661202
                ],
                [
                    36.0,
                    702.0
                ],
                [
                    41.71038251366121,
                    729.1001821493625
                ],
                [
                    46.44626593806922,
                    746.768670309654
                ],
                [
                    51.0,
                    765.3479052823316
                ],
                [
                    55.37158469945356,
                    772.6338797814208
                ],
                [
                    61.74681238615665,
                    776.8233151183971
                ],
                [
                    65.5719489981785,
                    771.5409836065575
                ],
                [
                    69.21493624772313,
                    772.9981785063752
                ],
                [
                    78.0,
                    773.0
                ],
                [
                    82.0,
                    783.0
                ],
                [
                    84.0,
                    785.0
                ],
                [
                    87.0,
                    785.0
                ],
                [
                    96.0,
                    777.0
                ],
                [
                    100.0,
                    776.0
                ],
                [
                    106.0,
                    767.0
                ],
                [
                    112.0,
                    767.0
                ],
                [
                    116.0,
                    762.0
                ],
                [
                    119.0,
                    762.0
                ],
                [
                    122.0,
                    765.0
                ],
                [
                    128.0,
                    767.0
                ],
                [
                    131.6,
                    782.0
                ],
                [
                    137.2,
                    774.8
                ],
                [
                    144.0,
                    768.0
                ],
                [
                    150.4,
                    758.8
                ],
                [
                    155.6,
                    748.8
                ],
                [
                    156.0,
                    736.0
                ],
                [
                    160.0,
                    731.0
                ],
                [
                    163.0,
                    721.0
                ],
                [
                    171.0,
                    721.0
                ],
                [
                    176.0,
                    717.0
                ],
                [
                    177.0,
                    722.0
                ],
                [
                    182.0,
                    724.0
                ],
                [
                    187.0,
                    718.0
                ],
                [
                    190.0,
                    717.0
                ],
                [
                    193.0,
                    723.0
                ],
                [
                    197.0,
                    725.0
                ],
                [
                    206.0,
                    715.0
                ],
                [
                    212.0,
                    714.0
                ],
                [
                    215.0,
                    717.0
                ],
                [
                    219.0,
                    717.0
                ],
                [
                    221.0,
                    713.0
                ],
                [
                    228.0,
                    708.0
                ],
                [
                    231.0,
                    708.0
                ],
                [
                    236.0,
                    711.0
                ],
                [
                    247.0,
                    711.0
                ],
                [
                    250.0,
                    714.0
                ],
                [
                    252.0,
                    720.0
                ],
                [
                    261.0,
                    710.0
                ],
                [
                    265.0,
                    713.0
                ],
                [
                    268.0,
                    718.0
                ],
                [
                    272.0,
                    720.0
                ],
                [
                    279.0,
                    714.0
                ],
                [
                    281.0,
                    710.0
                ],
                [
                    283.0,
                    710.0
                ],
                [
                    290.0,
                    714.4
                ],
                [
                    298.0,
                    728.8
                ],
                [
                    297.6,
                    713.2
                ],
                [
                    298.8,
                    589.6
                ],
                [
                    298.4,
                    454.8
                ],
                [
                    286.0,
                    456.0
                ],
                [
                    281.0,
                    449.0
                ],
                [
                    278.0,
                    449.0
                ],
                [
                    270.0,
                    461.0
                ],
                [
                    267.0,
                    461.0
                ],
                [
                    263.0,
                    458.0
                ],
                [
                    259.0,
                    458.0
                ],
                [
                    253.0,
                    465.0
                ],
                [
                    248.0,
                    457.0
                ],
                [
                    243.0,
                    454.0
                ],
                [
                    239.0,
                    449.0
                ],
                [
                    235.0,
                    449.0
                ],
                [
                    229.0,
                    446.0
                ],
                [
                    226.0,
                    449.0
                ],
                [
                    221.0,
                    449.0
                ],
                [
                    215.0,
                    459.0
                ],
                [
                    206.0,
                    460.0
                ],
                [
                    202.0,
                    469.0
                ],
                [
                    199.0,
                    469.0
                ],
                [
                    195.0,
                    475.0
                ],
                [
                    193.0,
                    473.0
                ],
                [
                    191.0,
                    461.0
                ],
                [
                    189.0,
                    460.0
                ],
                [
                    186.0,
                    464.0
                ],
                [
                    181.0,
                    465.0
                ],
                [
                    174.0,
                    463.0
                ],
                [
                    173.0,
                    460.0
                ],
                [
                    170.0,
                    458.0
                ],
                [
                    157.0,
                    466.0
                ],
                [
                    150.0,
                    462.8
                ],
                [
                    142.4,
                    461.2
                ],
                [
                    140.8,
                    462.4
                ],
                [
                    137.2,
                    455.6
                ],
                [
                    133.2,
                    469.2
                ],
                [
                    129.0,
                    469.0
                ],
                [
                    121.0,
                    464.0
                ],
                [
                    119.0,
                    459.0
                ],
                [
                    115.48087431693989,
                    458.79052823315124
                ],
                [
                    116.4,
                    448.0
                ],
                [
                    112.4,
                    444.4
                ],
                [
                    107.6,
                    446.8
                ],
                [
                    100.0,
                    451.0
                ],
                [
                    93.80510018214936,
                    454.0546448087432
                ],
                [
                    89.06921675774134,
                    454.6010928961749
                ],
                [
                    81.60109289617486,
                    446.9508196721312
                ],
                [
                    75.22586520947176,
                    444.7650273224044
                ],
                [
                    65.20765027322403,
                    446.040072859745
                ],
                [
                    61.74681238615665,
                    457.33333333333337
                ],
                [
                    59.743169398907106,
                    466.62295081967216
                ],
                [
                    54.64298724954463,
                    477.9162112932605
                ],
                [
                    48.449908925318766,
                    495.2204007285975
                ],
                [
                    41.16393442622951,
                    511.4316939890711
                ],
                [
                    36.61020036429873,
                    520.7213114754098
                ],
                [
                    33.33151183970856,
                    531.832422586521
                ]
            ],
            "group_id": null,
            "description": null,
            "shape_type": "polygon",
            "flags": {}
        }
    ],
    "imagePath": "1694352922.png",
    "imageData": null,
    "imageHeight": 1248,
    "imageWidth": 1248
}