{
    "version": "5.3.0",
    "flags": {},
    "shapes": [
        {
            "label": "weld",
            "points": [
                [
                    146.34146341463415,
                    668.2926829268292
                ],
                [
                    140.23376623376626,
                    608.4155844155844
                ],
                [
                    145.75324675324677,
                    605.4935064935064
                ],
                [
                    151.59740259740263,
                    601.5974025974026
                ],
                [
                    151.6260162601626,
                    591.0569105691058
                ],
                [
                    161.0,
                    581.0
                ],
                [
                    163.0,
                    581.0
                ],
                [
                    169.0,
                    587.0
                ],
                [
                    175.609756097561,
                    600.4065040650406
                ],
                [
                    182.0,
                    603.0
                ],
                [
                    187.0,
                    605.0
                ],
                [
                    190.35294117647058,
                    614.3529411764706
                ],
                [
                    195.76470588235293,
                    618.1176470588235
                ],
                [
                    200.7058823529412,
                    614.3529411764706
                ],
                [
                    204.47058823529412,
                    610.5882352941177
                ],
                [
                    206.8235294117647,
                    600.9411764705883
                ],
                [
                    208.47058823529412,
                    593.8823529411765
                ],
                [
                    210.0,
                    586.0
                ],
                [
                    215.0,
                    585.0
                ],
                [
                    233.0,
                    570.0
                ],
                [
                    238.0,
                    572.0
                ],
                [
                    240.0,
                    561.0
                ],
                [
                    243.0,
                    568.0
                ],
                [
                    248.0,
                    573.0
                ],
                [
                    261.0,
                    572.0
                ],
                [
                    267.0,
                    578.0
                ],
                [
                    269.0,
                    578.0
                ],
                [
                    283.0,
                    568.0
                ],
                [
                    298.0,
                    544.0
                ],
                [
                    303.0,
                    539.0
                ],
                [
                    306.0,
                    538.0
                ],
                [
                    309.0,
                    540.0
                ],
                [
                    315.0,
                    540.0
                ],
                [
                    321.0,
                    544.0
                ],
                [
                    327.0,
                    540.0
                ],
                [
                    329.0,
                    545.0
                ],
                [
                    332.0,
                    547.0
                ],
                [
                    339.0,
                    537.0
                ],
                [
                    346.0,
                    536.0
                ],
                [
                    347.0,
                    534.0
                ],
                [
                    349.0,
                    534.0
                ],
                [
                    352.0,
                    540.0
                ],
                [
                    357.0,
                    539.0
                ],
                [
                    366.0,
                    546.0
                ],
                [
                    374.0,
                    559.0
                ],
                [
                    384.0,
                    569.0
                ],
                [
                    393.0,
                    582.0
                ],
                [
                    412.0,
                    618.0
                ],
                [
                    414.0,
                    620.0
                ],
                [
                    417.01801801801804,
                    634.1351351351351
                ],
                [
                    418.3693693693694,
                    665.6666666666667
                ],
                [
                    420.0,
                    716.0
                ],
                [
                    418.2926829268293,
                    722.3577235772358
                ],
                [
                    415.0,
                    727.0
                ],
                [
                    413.0,
                    757.0
                ],
                [
                    406.0975609756098,
                    771.1382113821138
                ],
                [
                    404.8780487804878,
                    782.9268292682927
                ],
                [
                    399.5934959349594,
                    789.0243902439024
                ],
                [
                    396.7479674796748,
                    797.5609756097562
                ],
                [
                    392.6829268292683,
                    801.219512195122
                ],
                [
                    389.4308943089431,
                    805.2845528455284
                ],
                [
                    384.9593495934959,
                    806.5040650406504
                ],
                [
                    382.520325203252,
                    804.8780487804878
                ],
                [
                    379.6747967479675,
                    801.219512195122
                ],
                [
                    375.609756097561,
                    803.2520325203252
                ],
                [
                    371.1382113821138,
                    807.7235772357724
                ],
                [
                    364.0,
                    812.0
                ],
                [
                    360.1626016260163,
                    800.0
                ],
                [
                    354.0650406504065,
                    795.1219512195122
                ],
                [
                    347.5609756097561,
                    795.5284552845528
                ],
                [
                    340.650406504065,
                    792.6829268292684
                ],
                [
                    332.9268292682927,
                    794.308943089431
                ],
                [
                    322.3577235772358,
                    793.089430894309
                ],
                [
                    313.8211382113821,
                    790.650406504065
                ],
                [
                    309.349593495935,
                    783.3333333333334
                ],
                [
                    302.4390243902439,
                    774.390243902439
                ],
                [
                    297.1544715447155,
                    769.1056910569106
                ],
                [
                    289.0243902439024,
                    773.9837398373984
                ],
                [
                    282.9268292682927,
                    781.3008130081301
                ],
                [
                    276.4227642276423,
                    786.178861788618
                ],
                [
                    270.3252032520325,
                    789.8373983739838
                ],
                [
                    259.7560975609756,
                    786.5853658536586
                ],
                [
                    250.8130081300813,
                    778.4552845528456
                ],
                [
                    246.7479674796748,
                    762.6016260162602
                ],
                [
                    240.65040650406505,
                    750.8130081300814
                ],
                [
                    231.70731707317074,
                    745.1219512195122
                ],
                [
                    224.7967479674797,
                    744.7154471544716
                ],
                [
                    219.10569105691056,
                    747.5609756097562
                ],
                [
                    213.41463414634146,
                    766.260162601626
                ],
                [
                    212.31168831168833,
                    777.8961038961039
                ],
                [
                    210.16260162601625,
                    782.9268292682927
                ],
                [
                    206.0,
                    787.0
                ],
                [
                    203.0,
                    788.0
                ],
                [
                    197.96747967479675,
                    791.4634146341464
                ],
                [
                    195.52845528455285,
                    797.5609756097562
                ],
                [
                    189.4308943089431,
                    802.8455284552846
                ],
                [
                    183.739837398374,
                    800.4065040650406
                ],
                [
                    178.0,
                    795.0
                ],
                [
                    159.0649350649351,
                    748.0259740259739
                ],
                [
                    153.65853658536585,
                    720.7317073170732
                ],
                [
                    149.974025974026,
                    692.1818181818181
                ],
                [
                    147.3766233766234,
                    682.1168831168831
                ]
            ],
            "group_id": null,
            "description": null,
            "shape_type": "polygon",
            "flags": {}
        },
        {
            "label": "weld",
            "points": [
                [
                    752.0,
                    988.5
                ],
                [
                    742.0,
                    986.5
                ],
                [
                    726.0,
                    968.5
                ],
                [
                    687.0,
                    946.5
                ],
                [
                    604.0,
                    916.5
                ],
                [
                    595.5,
                    908.0
                ],
                [
                    582.5,
                    875.0
                ],
                [
                    573.0,
                    872.5
                ],
                [
                    568.0,
                    864.5
                ],
                [
                    564.0,
                    862.5
                ],
                [
                    546.0,
                    879.5
                ],
                [
                    535.0,
                    878.5
                ],
                [
                    524.5,
                    865.0
                ],
                [
                    512.5,
                    823.0
                ],
                [
                    511.5,
                    686.0
                ],
                [
                    535.0,
                    674.5
                ],
                [
                    555.0,
                    647.5
                ],
                [
                    568.0,
                    643.5
                ],
                [
                    578.0,
                    648.5
                ],
                [
                    612.0,
                    647.5
                ],
                [
                    648.0,
                    662.5
                ],
                [
                    661.0,
                    674.5
                ],
                [
                    702.0,
                    679.5
                ],
                [
                    724.5,
                    695.0
                ],
                [
                    740.5,
                    733.0
                ],
                [
                    754.5,
                    804.0
                ],
                [
                    777.0,
                    815.5
                ],
                [
                    783.5,
                    825.0
                ],
                [
                    778.5,
                    931.0
                ],
                [
                    769.5,
                    963.0
                ],
                [
                    759.5,
                    984.0
                ]
            ],
            "group_id": null,
            "description": "",
            "shape_type": "polygon",
            "flags": {}
        }
    ],
    "imagePath": "1697063023.png",
    "imageData": null,
    "imageHeight": 1248,
    "imageWidth": 1248
}