{
    "version": "5.3.0",
    "flags": {},
    "shapes": [
        {
            "label": "weld",
            "points": [
                [
                    236.5942028985507,
                    611.9565217391304
                ],
                [
                    236.9565217391304,
                    643.8405797101449
                ],
                [
                    235.14492753623188,
                    663.7681159420289
                ],
                [
                    234.42028985507244,
                    755.0724637681159
                ],
                [
                    242.4,
                    780.0
                ],
                [
                    246.4,
                    787.6
                ],
                [
                    250.4,
                    791.6
                ],
                [
                    255.0,
                    785.0
                ],
                [
                    260.4,
                    780.8
                ],
                [
                    264.4,
                    771.2
                ],
                [
                    270.0,
                    759.2
                ],
                [
                    270.8,
                    792.4
                ],
                [
                    278.0,
                    781.0
                ],
                [
                    286.0,
                    773.0
                ],
                [
                    296.0,
                    770.4
                ],
                [
                    304.0,
                    773.2
                ],
                [
                    313.6,
                    776.4
                ],
                [
                    327.0,
                    776.0
                ],
                [
                    331.0,
                    778.0
                ],
                [
                    338.76811594202894,
                    777.1739130434783
                ],
                [
                    349.63768115942025,
                    775.3623188405796
                ],
                [
                    359.42028985507244,
                    771.7391304347825
                ],
                [
                    371.73913043478257,
                    771.7391304347825
                ],
                [
                    380.7971014492753,
                    774.9999999999999
                ],
                [
                    386.231884057971,
                    777.5362318840579
                ],
                [
                    391.30434782608694,
                    777.5362318840579
                ],
                [
                    395.0,
                    777.0
                ],
                [
                    401.08695652173907,
                    769.2028985507246
                ],
                [
                    409.78260869565213,
                    768.4782608695651
                ],
                [
                    416.0,
                    774.0
                ],
                [
                    422.8260869565217,
                    776.086956521739
                ],
                [
                    428.62318840579707,
                    775.3623188405796
                ],
                [
                    434.78260869565213,
                    774.6376811594203
                ],
                [
                    444.927536231884,
                    780.0724637681159
                ],
                [
                    450.7246376811594,
                    793.4782608695651
                ],
                [
                    455.7971014492753,
                    801.086956521739
                ],
                [
                    460.0,
                    807.0
                ],
                [
                    471.0,
                    840.0
                ],
                [
                    476.4,
                    854.0
                ],
                [
                    478.0,
                    837.6
                ],
                [
                    480.8,
                    807.6
                ],
                [
                    484.4,
                    803.2
                ],
                [
                    488.4,
                    807.2
                ],
                [
                    488.0,
                    822.0
                ],
                [
                    489.4927536231884,
                    839.4927536231884
                ],
                [
                    498.1884057971014,
                    834.7826086956521
                ],
                [
                    502.1739130434782,
                    830.4347826086956
                ],
                [
                    506.159420289855,
                    824.9999999999999
                ],
                [
                    512.6811594202898,
                    820.6521739130434
                ],
                [
                    517.7536231884058,
                    809.0579710144926
                ],
                [
                    526.0869565217391,
                    783.695652173913
                ],
                [
                    531.0,
                    653.0
                ],
                [
                    528.623188405797,
                    539.4927536231884
                ],
                [
                    517.0,
                    482.0
                ],
                [
                    505.0,
                    410.0
                ],
                [
                    497.0,
                    387.0
                ],
                [
                    494.0,
                    385.0
                ],
                [
                    488.0,
                    384.0
                ],
                [
                    485.0,
                    393.0
                ],
                [
                    474.99999999999994,
                    456.52173913043475
                ],
                [
                    471.01449275362313,
                    450.7246376811594
                ],
                [
                    465.5797101449275,
                    440.2173913043478
                ],
                [
                    464.85507246376807,
                    430.0724637681159
                ],
                [
                    457.97101449275357,
                    423.5507246376811
                ],
                [
                    451.8115942028985,
                    421.73913043478257
                ],
                [
                    440.5797101449275,
                    416.30434782608694
                ],
                [
                    433.3333333333333,
                    419.5652173913043
                ],
                [
                    427.53623188405794,
                    422.463768115942
                ],
                [
                    421.73913043478257,
                    425.7246376811594
                ],
                [
                    415.5797101449275,
                    428.2608695652174
                ],
                [
                    409.78260869565213,
                    426.4492753623188
                ],
                [
                    401.08695652173907,
                    426.08695652173907
                ],
                [
                    392.39130434782606,
                    424.63768115942025
                ],
                [
                    386.231884057971,
                    426.08695652173907
                ],
                [
                    378.2608695652174,
                    427.53623188405794
                ],
                [
                    371.01449275362313,
                    429.3478260869565
                ],
                [
                    365.2173913043478,
                    431.52173913043475
                ],
                [
                    356.88405797101444,
                    434.78260869565213
                ],
                [
                    350.7246376811594,
                    438.76811594202894
                ],
                [
                    346.3768115942029,
                    444.2028985507246
                ],
                [
                    341.66666666666663,
                    447.8260869565217
                ],
                [
                    336.231884057971,
                    448.9130434782608
                ],
                [
                    329.7101449275362,
                    450.3623188405797
                ],
                [
                    310.86956521739125,
                    455.0724637681159
                ],
                [
                    303.2608695652174,
                    456.88405797101444
                ],
                [
                    294.2028985507246,
                    456.52173913043475
                ],
                [
                    287.6811594202898,
                    456.52173913043475
                ],
                [
                    280.07246376811594,
                    455.0724637681159
                ],
                [
                    276.0,
                    456.0
                ],
                [
                    271.0,
                    451.0
                ],
                [
                    269.0,
                    451.0
                ],
                [
                    257.0,
                    466.0
                ],
                [
                    250.0,
                    490.0
                ],
                [
                    248.91304347826085,
                    500.3623188405797
                ],
                [
                    243.4782608695652,
                    525.3623188405796
                ],
                [
                    238.76811594202897,
                    549.6376811594203
                ]
            ],
            "group_id": null,
            "description": null,
            "shape_type": "polygon",
            "flags": {}
        }
    ],
    "imagePath": "1694291366.png",
    "imageData": null,
    "imageHeight": 1248,
    "imageWidth": 1248
}