{
    "version": "5.3.0",
    "flags": {},
    "shapes": [
        {
            "label": "weld",
            "points": [
                [
                    26.0,
                    718.5
                ],
                [
                    29.5,
                    755.5
                ],
                [
                    30.0,
                    762.0
                ],
                [
                    33.0,
                    771.0
                ],
                [
                    40.0,
                    806.0
                ],
                [
                    50.0,
                    840.0
                ],
                [
                    53.0,
                    844.0
                ],
                [
                    57.0,
                    866.0
                ],
                [
                    60.0,
                    872.0
                ],
                [
                    62.0,
                    872.0
                ],
                [
                    64.0,
                    869.0
                ],
                [
                    73.0,
                    836.0
                ],
                [
                    88.0,
                    809.0
                ],
                [
                    91.0,
                    809.0
                ],
                [
                    98.0,
                    816.0
                ],
                [
                    106.0,
                    815.0
                ],
                [
                    115.0,
                    825.0
                ],
                [
                    118.0,
                    824.0
                ],
                [
                    122.0,
                    814.0
                ],
                [
                    125.0,
                    814.0
                ],
                [
                    129.0,
                    817.0
                ],
                [
                    132.0,
                    815.0
                ],
                [
                    138.0,
                    821.0
                ],
                [
                    148.0,
                    807.0
                ],
                [
                    153.0,
                    807.0
                ],
                [
                    160.0,
                    793.0
                ],
                [
                    166.0,
                    810.0
                ],
                [
                    175.0,
                    816.0
                ],
                [
                    183.0,
                    832.0
                ],
                [
                    189.0,
                    826.0
                ],
                [
                    193.0,
                    855.0
                ],
                [
                    199.0,
                    853.5
                ],
                [
                    204.0,
                    854.5
                ],
                [
                    207.0,
                    847.0
                ],
                [
                    212.0,
                    818.0
                ],
                [
                    215.61889250814332,
                    795.4169381107492
                ],
                [
                    218.38762214983714,
                    779.6188925081434
                ],
                [
                    221.80781758957653,
                    649.0
                ],
                [
                    221.15635179153094,
                    630.1074918566776
                ],
                [
                    219.0,
                    566.0
                ],
                [
                    221.5,
                    541.0
                ],
                [
                    222.5,
                    521.5
                ],
                [
                    224.25081433224756,
                    482.2247557003258
                ],
                [
                    221.80781758957653,
                    469.35830618892516
                ],
                [
                    216.92182410423453,
                    462.6807817589577
                ],
                [
                    213.50162866449512,
                    456.8175895765473
                ],
                [
                    208.0,
                    461.2
                ],
                [
                    201.6,
                    455.6
                ],
                [
                    195.6,
                    450.0
                ],
                [
                    190.0,
                    459.0
                ],
                [
                    184.0,
                    465.6
                ],
                [
                    179.2,
                    460.0
                ],
                [
                    173.6,
                    459.2
                ],
                [
                    164.0,
                    454.0
                ],
                [
                    160.0,
                    452.0
                ],
                [
                    158.0,
                    449.0
                ],
                [
                    155.0,
                    449.0
                ],
                [
                    152.0,
                    446.0
                ],
                [
                    150.0,
                    446.0
                ],
                [
                    147.0,
                    449.0
                ],
                [
                    141.0,
                    451.0
                ],
                [
                    137.6,
                    456.4
                ],
                [
                    133.6,
                    461.6
                ],
                [
                    129.0,
                    453.0
                ],
                [
                    121.0,
                    453.0
                ],
                [
                    117.0,
                    455.0
                ],
                [
                    112.4,
                    450.4
                ],
                [
                    106.0,
                    452.8
                ],
                [
                    103.2,
                    444.0
                ],
                [
                    95.2,
                    442.0
                ],
                [
                    90.0,
                    444.0
                ],
                [
                    88.4,
                    453.6
                ],
                [
                    83.6,
                    441.6
                ],
                [
                    75.0,
                    439.0
                ],
                [
                    71.0,
                    437.0
                ],
                [
                    60.0,
                    452.0
                ],
                [
                    56.0,
                    456.0
                ],
                [
                    52.0,
                    449.6
                ],
                [
                    47.2,
                    451.2
                ],
                [
                    36.4,
                    468.0
                ],
                [
                    32.8,
                    481.6
                ],
                [
                    30.8,
                    498.0
                ],
                [
                    23.0,
                    636.0
                ]
            ],
            "group_id": null,
            "description": null,
            "shape_type": "polygon",
            "flags": {}
        }
    ],
    "imagePath": "1693748864.png",
    "imageData": null,
    "imageHeight": 1248,
    "imageWidth": 1248
}