{
    "version": "5.3.0",
    "flags": {},
    "shapes": [
        {
            "label": "weld",
            "points": [
                [
                    487.0,
                    737.5
                ],
                [
                    472.8476821192053,
                    741.0596026490066
                ],
                [
                    457.0,
                    728.5
                ],
                [
                    433.112582781457,
                    728.476821192053
                ],
                [
                    415.89403973509934,
                    735.0993377483444
                ],
                [
                    385.43046357615896,
                    729.1390728476821
                ],
                [
                    343.0,
                    732.5
                ],
                [
                    313.0,
                    723.5
                ],
                [
                    283.0,
                    732.5
                ],
                [
                    244.3708609271523,
                    721.8543046357615
                ],
                [
                    208.60927152317882,
                    725.8278145695364
                ],
                [
                    182.0,
                    715.5
                ],
                [
                    140.0,
                    720.5
                ],
                [
                    107.28476821192054,
                    723.1788079470199
                ],
                [
                    99.33774834437087,
                    708.6092715231788
                ],
                [
                    94.5,
                    688.0
                ],
                [
                    88.5,
                    588.0
                ],
                [
                    87.41721854304636,
                    520.5298013245033
                ],
                [
                    94.5,
                    472.0
                ],
                [
                    111.25827814569536,
                    464.9006622516556
                ],
                [
                    125.0,
                    463.5
                ],
                [
                    145.6953642384106,
                    470.19867549668874
                ],
                [
                    188.0794701986755,
                    466.887417218543
                ],
                [
                    211.25827814569536,
                    478.1456953642384
                ],
                [
                    237.08609271523179,
                    471.52317880794703
                ],
                [
                    272.0,
                    481.5
                ],
                [
                    293.3774834437086,
                    480.1324503311258
                ],
                [
                    313.2450331125828,
                    472.8476821192053
                ],
                [
                    341.72185430463577,
                    482.11920529801324
                ],
                [
                    364.2384105960265,
                    478.8079470198675
                ],
                [
                    394.0,
                    482.5
                ],
                [
                    421.0,
                    491.5
                ],
                [
                    447.01986754966885,
                    484.7682119205298
                ],
                [
                    465.5629139072848,
                    486.0927152317881
                ],
                [
                    512.0,
                    482.5
                ],
                [
                    532.4503311258278,
                    486.7549668874172
                ],
                [
                    569.0,
                    499.5
                ],
                [
                    580.5,
                    520.0
                ],
                [
                    584.5,
                    553.0
                ],
                [
                    577.5,
                    671.0
                ],
                [
                    562.2516556291391,
                    723.841059602649
                ],
                [
                    550.0,
                    734.5
                ],
                [
                    514.0,
                    730.5
                ]
            ],
            "group_id": null,
            "description": "",
            "shape_type": "polygon",
            "flags": {}
        }
    ],
    "imagePath": "1697066420.png",
    "imageData": null,
    "imageHeight": 1248,
    "imageWidth": 1248
}