{
    "version": "5.3.0",
    "flags": {},
    "shapes": [
        {
            "label": "weld",
            "points": [
                [
                    162.0,
                    575.5
                ],
                [
                    141.82945736434112,
                    569.7364341085271
                ],
                [
                    120.89922480620157,
                    576.7131782945736
                ],
                [
                    109.27131782945739,
                    534.8527131782946
                ],
                [
                    104.5,
                    470.0
                ],
                [
                    122.5,
                    417.0
                ],
                [
                    134.5,
                    334.0
                ],
                [
                    147.0,
                    320.5
                ],
                [
                    202.0,
                    300.5
                ],
                [
                    248.8062015503876,
                    315.47286821705427
                ],
                [
                    283.68992248062017,
                    310.8217054263566
                ],
                [
                    319.0,
                    318.5
                ],
                [
                    374.0,
                    311.5
                ],
                [
                    393.0,
                    318.5
                ],
                [
                    432.52713178294573,
                    320.1240310077519
                ],
                [
                    468.1860465116279,
                    310.8217054263566
                ],
                [
                    488.0,
                    319.5
                ],
                [
                    538.0,
                    304.5
                ],
                [
                    555.5,
                    316.0
                ],
                [
                    568.5,
                    365.0
                ],
                [
                    568.1860465116279,
                    464.31007751937983
                ],
                [
                    554.5,
                    552.0
                ],
                [
                    548.031007751938,
                    565.0852713178294
                ],
                [
                    535.0,
                    569.5
                ],
                [
                    441.0,
                    560.5
                ],
                [
                    376.71317829457365,
                    562.7596899224806
                ],
                [
                    353.0,
                    570.5
                ],
                [
                    273.61240310077517,
                    564.3100775193799
                ],
                [
                    247.2558139534884,
                    572.062015503876
                ],
                [
                    190.0,
                    569.5
                ]
            ],
            "group_id": null,
            "description": "",
            "shape_type": "polygon",
            "flags": {}
        }
    ],
    "imagePath": "1697063931.png",
    "imageData": null,
    "imageHeight": 1248,
    "imageWidth": 1248
}