{
    "version": "5.3.0",
    "flags": {},
    "shapes": [
        {
            "label": "weld",
            "points": [
                [
                    24.044943820224717,
                    650.5168539325842
                ],
                [
                    25.39325842696629,
                    694.7865168539325
                ],
                [
                    27.0,
                    705.0
                ],
                [
                    31.0,
                    729.0
                ],
                [
                    37.0,
                    734.0
                ],
                [
                    47.0,
                    729.0
                ],
                [
                    54.8,
                    723.6
                ],
                [
                    63.6,
                    724.4
                ],
                [
                    69.6,
                    726.8
                ],
                [
                    80.4,
                    731.2
                ],
                [
                    90.0,
                    729.6
                ],
                [
                    99.2,
                    732.0
                ],
                [
                    104.4,
                    724.8
                ],
                [
                    109.2,
                    723.2
                ],
                [
                    111.6,
                    716.4
                ],
                [
                    116.4,
                    722.8
                ],
                [
                    121.0,
                    715.0
                ],
                [
                    126.0,
                    702.0
                ],
                [
                    131.2,
                    707.6
                ],
                [
                    135.6,
                    716.4
                ],
                [
                    141.2,
                    715.2
                ],
                [
                    145.0,
                    703.0
                ],
                [
                    149.0,
                    704.0
                ],
                [
                    152.4,
                    720.4
                ],
                [
                    156.0,
                    732.4
                ],
                [
                    163.2,
                    732.4
                ],
                [
                    165.0,
                    719.0
                ],
                [
                    169.0,
                    711.0
                ],
                [
                    180.0,
                    725.0
                ],
                [
                    185.0,
                    729.0
                ],
                [
                    187.0,
                    728.0
                ],
                [
                    192.0,
                    719.0
                ],
                [
                    194.0,
                    719.0
                ],
                [
                    201.0,
                    728.0
                ],
                [
                    207.0,
                    722.0
                ],
                [
                    211.0,
                    730.0
                ],
                [
                    217.0,
                    733.0
                ],
                [
                    225.0,
                    730.0
                ],
                [
                    233.0,
                    722.0
                ],
                [
                    235.0,
                    722.0
                ],
                [
                    247.0,
                    740.0
                ],
                [
                    250.0,
                    741.0
                ],
                [
                    256.0,
                    733.0
                ],
                [
                    268.0,
                    733.0
                ],
                [
                    269.0,
                    731.0
                ],
                [
                    274.0,
                    734.0
                ],
                [
                    282.0,
                    736.0
                ],
                [
                    294.0,
                    754.0
                ],
                [
                    296.0,
                    754.0
                ],
                [
                    301.0,
                    749.0
                ],
                [
                    313.0,
                    753.0
                ],
                [
                    325.0,
                    741.0
                ],
                [
                    328.0,
                    742.0
                ],
                [
                    333.0,
                    754.0
                ],
                [
                    340.0,
                    761.0
                ],
                [
                    353.0,
                    746.0
                ],
                [
                    359.0,
                    744.0
                ],
                [
                    360.0,
                    498.83146067415737
                ],
                [
                    356.0,
                    496.0
                ],
                [
                    347.86516853932585,
                    495.9101123595506
                ],
                [
                    338.2022471910112,
                    500.6292134831461
                ],
                [
                    332.5842696629213,
                    492.53932584269666
                ],
                [
                    328.4,
                    492.0
                ],
                [
                    324.4,
                    494.8
                ],
                [
                    319.6,
                    502.0
                ],
                [
                    314.0,
                    513.2
                ],
                [
                    306.4,
                    516.4
                ],
                [
                    299.2,
                    514.0
                ],
                [
                    293.2,
                    515.2
                ],
                [
                    285.6,
                    501.2
                ],
                [
                    280.0,
                    492.0
                ],
                [
                    274.0,
                    496.0
                ],
                [
                    272.0,
                    500.0
                ],
                [
                    269.0,
                    502.0
                ],
                [
                    262.0,
                    498.0
                ],
                [
                    256.0,
                    502.4
                ],
                [
                    250.8,
                    503.6
                ],
                [
                    242.0,
                    501.0
                ],
                [
                    235.0,
                    500.0
                ],
                [
                    230.0,
                    509.0
                ],
                [
                    226.0,
                    513.0
                ],
                [
                    224.0,
                    513.0
                ],
                [
                    214.0,
                    504.0
                ],
                [
                    210.0,
                    497.0
                ],
                [
                    202.0,
                    497.0
                ],
                [
                    200.0,
                    495.0
                ],
                [
                    195.6,
                    479.6
                ],
                [
                    190.8,
                    473.2
                ],
                [
                    186.0,
                    483.0
                ],
                [
                    180.0,
                    474.0
                ],
                [
                    177.0,
                    462.0
                ],
                [
                    173.0,
                    460.0
                ],
                [
                    170.0,
                    454.0
                ],
                [
                    166.0,
                    460.0
                ],
                [
                    160.4,
                    470.0
                ],
                [
                    158.4,
                    453.2
                ],
                [
                    158.0,
                    438.0
                ],
                [
                    155.0,
                    423.0
                ],
                [
                    152.8,
                    414.0
                ],
                [
                    144.4,
                    390.4
                ],
                [
                    136.4,
                    404.8
                ],
                [
                    130.0,
                    418.0
                ],
                [
                    124.0,
                    403.0
                ],
                [
                    122.0,
                    404.0
                ],
                [
                    117.0,
                    415.0
                ],
                [
                    114.0,
                    415.0
                ],
                [
                    112.0,
                    413.0
                ],
                [
                    107.0,
                    404.0
                ],
                [
                    104.0,
                    404.0
                ],
                [
                    97.0,
                    409.0
                ],
                [
                    94.0,
                    416.0
                ],
                [
                    91.0,
                    417.0
                ],
                [
                    88.0,
                    412.0
                ],
                [
                    86.0,
                    399.0
                ],
                [
                    80.0,
                    394.4
                ],
                [
                    78.42696629213482,
                    384.89887640449444
                ],
                [
                    74.3820224719101,
                    381.3033707865169
                ],
                [
                    71.01123595505618,
                    384.22471910112364
                ],
                [
                    70.0,
                    410.0
                ],
                [
                    70.4,
                    422.8
                ],
                [
                    70.4,
                    454.4
                ],
                [
                    66.4,
                    453.6
                ],
                [
                    63.2,
                    443.6
                ],
                [
                    58.4,
                    449.6
                ],
                [
                    51.6,
                    459.6
                ],
                [
                    44.8,
                    468.4
                ],
                [
                    42.8,
                    476.4
                ],
                [
                    39.10112359550562,
                    485.79775280898883
                ],
                [
                    29.662921348314605,
                    526.9213483146067
                ],
                [
                    27.640449438202246,
                    533.6629213483146
                ],
                [
                    25.0,
                    616.0
                ]
            ],
            "group_id": null,
            "description": null,
            "shape_type": "polygon",
            "flags": {}
        }
    ],
    "imagePath": "1694260900.png",
    "imageData": null,
    "imageHeight": 1248,
    "imageWidth": 1248
}