{
    "version": "5.3.0",
    "flags": {},
    "shapes": [
        {
            "label": "weld",
            "points": [
                [
                    183.0,
                    471.0
                ],
                [
                    190.0,
                    438.0
                ],
                [
                    205.0,
                    407.0
                ],
                [
                    209.0,
                    404.0
                ],
                [
                    215.2955465587045,
                    398.2914979757086
                ],
                [
                    225.41700404858304,
                    398.2914979757086
                ],
                [
                    231.89473684210532,
                    398.2914979757086
                ],
                [
                    237.15789473684217,
                    405.174089068826
                ],
                [
                    242.01619433198385,
                    408.8178137651823
                ],
                [
                    248.49392712550613,
                    410.842105263158
                ],
                [
                    254.56680161943325,
                    406.3886639676114
                ],
                [
                    261.04453441295556,
                    407.60323886639685
                ],
                [
                    267.11740890688264,
                    405.5789473684211
                ],
                [
                    273.1902834008098,
                    410.4372469635628
                ],
                [
                    281.28744939271263,
                    410.0323886639677
                ],
                [
                    288.0,
                    415.0
                ],
                [
                    297.0,
                    413.0
                ],
                [
                    302.0,
                    420.0
                ],
                [
                    305.0,
                    420.0
                ],
                [
                    311.24696356275314,
                    418.1295546558705
                ],
                [
                    316.1052631578948,
                    419.3441295546559
                ],
                [
                    320.9635627530365,
                    419.7489878542511
                ],
                [
                    324.20242914979764,
                    419.3441295546559
                ],
                [
                    329.4655870445345,
                    417.7246963562754
                ],
                [
                    335.1336032388665,
                    418.9392712550608
                ],
                [
                    341.0,
                    421.0
                ],
                [
                    349.7085020242916,
                    419.7489878542511
                ],
                [
                    356.18623481781384,
                    414.48582995951426
                ],
                [
                    363.8785425101215,
                    416.51012145748996
                ],
                [
                    369.95141700404866,
                    415.7004048582997
                ],
                [
                    378.8582995951418,
                    415.29554655870453
                ],
                [
                    384.0,
                    414.0
                ],
                [
                    387.0,
                    415.0
                ],
                [
                    395.45748987854256,
                    416.91497975708506
                ],
                [
                    406.0,
                    416.0
                ],
                [
                    414.48582995951426,
                    413.67611336032394
                ],
                [
                    420.9635627530365,
                    417.3198380566802
                ],
                [
                    426.6315789473685,
                    415.7004048582997
                ],
                [
                    434.72874493927134,
                    410.4372469635628
                ],
                [
                    440.8016194331984,
                    409.2226720647774
                ],
                [
                    447.68421052631584,
                    407.1983805668017
                ],
                [
                    451.7327935222673,
                    400.3157894736843
                ],
                [
                    457.0,
                    393.0
                ],
                [
                    461.0,
                    393.0
                ],
                [
                    467.0,
                    395.0
                ],
                [
                    472.1822541966427,
                    405.99520383693044
                ],
                [
                    478.8968824940048,
                    408.63309352517985
                ],
                [
                    489.0,
                    416.0
                ],
                [
                    498.0,
                    440.0
                ],
                [
                    507.0,
                    482.0
                ],
                [
                    508.0,
                    577.0
                ],
                [
                    508.0,
                    577.0
                ],
                [
                    503.5546558704454,
                    659.82995951417
                ],
                [
                    503.14979757085024,
                    678.8582995951417
                ],
                [
                    502.0,
                    691.0
                ],
                [
                    500.0,
                    706.0
                ],
                [
                    490.0,
                    748.0
                ],
                [
                    484.0,
                    759.0
                ],
                [
                    479.1044776119403,
                    767.1641791044775
                ],
                [
                    471.26865671641787,
                    767.3507462686566
                ],
                [
                    466.2313432835821,
                    761.3805970149253
                ],
                [
                    456.0,
                    755.0
                ],
                [
                    445.0,
                    745.0
                ],
                [
                    434.5149253731343,
                    748.5074626865671
                ],
                [
                    423.69402985074623,
                    750.1865671641791
                ],
                [
                    417.5373134328358,
                    750.0
                ],
                [
                    409.0,
                    752.0
                ],
                [
                    402.0,
                    760.0
                ],
                [
                    393.0,
                    757.0
                ],
                [
                    386.0,
                    763.0
                ],
                [
                    379.0,
                    763.0
                ],
                [
                    375.0,
                    769.0
                ],
                [
                    372.0,
                    769.0
                ],
                [
                    367.0,
                    765.0
                ],
                [
                    358.3955223880597,
                    772.9477611940298
                ],
                [
                    356.0,
                    782.0
                ],
                [
                    351.0,
                    787.0
                ],
                [
                    343.0,
                    786.0
                ],
                [
                    338.0,
                    790.0
                ],
                [
                    329.0,
                    791.0
                ],
                [
                    322.0,
                    789.0
                ],
                [
                    318.0,
                    791.0
                ],
                [
                    307.0,
                    791.0
                ],
                [
                    300.0,
                    786.0
                ],
                [
                    297.0,
                    786.0
                ],
                [
                    291.0,
                    790.0
                ],
                [
                    284.0,
                    783.0
                ],
                [
                    279.0,
                    783.0
                ],
                [
                    276.0,
                    785.0
                ],
                [
                    270.0,
                    779.0
                ],
                [
                    265.0,
                    779.0
                ],
                [
                    246.82835820895522,
                    783.5820895522388
                ],
                [
                    236.0,
                    786.0
                ],
                [
                    226.0,
                    777.0
                ],
                [
                    221.0,
                    777.0
                ],
                [
                    216.04477611940297,
                    774.6268656716418
                ],
                [
                    207.83582089552237,
                    768.6567164179104
                ],
                [
                    201.3059701492537,
                    768.2835820895522
                ],
                [
                    194.0,
                    747.0
                ],
                [
                    188.0,
                    726.0
                ],
                [
                    186.0,
                    702.0
                ],
                [
                    183.0,
                    698.0
                ],
                [
                    182.0,
                    549.0
                ]
            ],
            "group_id": null,
            "description": null,
            "shape_type": "polygon",
            "flags": {}
        }
    ],
    "imagePath": "1697063688.png",
    "imageData": null,
    "imageHeight": 1248,
    "imageWidth": 1248
}